com_digitalruiz_my_logger/__init__.py
com_digitalruiz_my_logger/my_logger.py
com_digitalruiz_my_logger-0.0.4.dist-info/LICENSE
com_digitalruiz_my_logger-0.0.4.dist-info/METADATA
com_digitalruiz_my_logger-0.0.4.dist-info/WHEEL
com_digitalruiz_my_logger-0.0.4.dist-info/top_level.txt
com_digitalruiz_my_logger-0.0.4.dist-info/RECORD
